gfss_microsoft/__init__.py
gfss_alteryx_devkit-0.0.1.dist-info/METADATA
gfss_alteryx_devkit-0.0.1.dist-info/WHEEL
gfss_alteryx_devkit-0.0.1.dist-info/top_level.txt
gfss_alteryx_devkit-0.0.1.dist-info/RECORD
